FiberPI/FiberPI.py
FiberPI/__init__.py
FiberPI-0.0.3.dist-info/LICENSE
FiberPI-0.0.3.dist-info/METADATA
FiberPI-0.0.3.dist-info/WHEEL
FiberPI-0.0.3.dist-info/top_level.txt
FiberPI-0.0.3.dist-info/RECORD
