Metadata-Version: 2.1
Name: FiberPI
Version: 0.0.3
Summary: Package to detect contaminated fiber connectors
Home-page: https://github.com/utepnetlab/fiberPI
Author: Christopher Mendoza
Author-email: camendoza7@miners.utep.edu
License: UNKNOWN
Platform: UNKNOWN
Classifier: Programming Language :: Python :: 3
Classifier: License :: OSI Approved :: MIT License
Classifier: Operating System :: OS Independent
